{"appleSKU":"","appleTeamID":"","enableCodelessAutoInitialization":true,"enableUnityGamingServicesAutoInitialization":true,"products":[{"id":"com.zherish.aballgame.purchaseall","type":1,"storeIDs":[],"defaultDescription":{"googleLocale":4,"title":"Purchase All","description":"Unlock all balls with different abilities and remove ads."},"screenshotPath":"","applePriceTier":0,"googlePrice":{"data":[59,0,0,0],"num":59.0},"pricingTemplateID":"","descriptions":[],"udpPrice":{"data":[0,0,0,0],"num":0.0},"payouts":[]}]}